{
	"configurations" : 
	[
		{
			"directories" : 
			[
				{
					"build" : ".",
					"jsonFile" : "directory-.-Debug-d0094a50bb2071803777.json",
					"minimumCMakeVersion" : 
					{
						"string" : "3.16"
					},
					"projectIndex" : 0,
					"source" : ".",
					"targetIndexes" : 
					[
						0,
						1,
						2
					]
				}
			],
			"name" : "Debug",
			"projects" : 
			[
				{
					"directoryIndexes" : 
					[
						0
					],
					"name" : "lab3",
					"targetIndexes" : 
					[
						0,
						1,
						2
					]
				}
			],
			"targets" : 
			[
				{
					"directoryIndex" : 0,
					"id" : "lab3::@6890427a1f51a3e7e1df",
					"jsonFile" : "target-lab3-Debug-edb8008129398a83d73e.json",
					"name" : "lab3",
					"projectIndex" : 0
				},
				{
					"directoryIndex" : 0,
					"id" : "lab3_autogen::@6890427a1f51a3e7e1df",
					"jsonFile" : "target-lab3_autogen-Debug-344dc004175bb592be25.json",
					"name" : "lab3_autogen",
					"projectIndex" : 0
				},
				{
					"directoryIndex" : 0,
					"id" : "lab3_autogen_timestamp_deps::@6890427a1f51a3e7e1df",
					"jsonFile" : "target-lab3_autogen_timestamp_deps-Debug-29a8847eefd155ffa8af.json",
					"name" : "lab3_autogen_timestamp_deps",
					"projectIndex" : 0
				}
			]
		}
	],
	"kind" : "codemodel",
	"paths" : 
	{
		"build" : "C:/Users/Michael/ROOT/MEPHI/sem3/labs/Lab3/build",
		"source" : "C:/Users/Michael/ROOT/MEPHI/sem3/labs/Lab3"
	},
	"version" : 
	{
		"major" : 2,
		"minor" : 7
	}
}
